GitData/__init__.py
GitData/core.py
GitGrabber-0.0.1.dist-info/LICENSE
GitGrabber-0.0.1.dist-info/METADATA
GitGrabber-0.0.1.dist-info/WHEEL
GitGrabber-0.0.1.dist-info/top_level.txt
GitGrabber-0.0.1.dist-info/zip-safe
GitGrabber-0.0.1.dist-info/RECORD
